pvradar/sdk/__init__.py
pvradar/sdk/__main__.py
pvradar/sdk/caching/__init__.py
pvradar/sdk/caching/cache_binder.py
pvradar/sdk/caching/caching_factory.py
pvradar/sdk/caching/caching_handler.py
pvradar/sdk/caching/caching_output_filter.py
pvradar/sdk/caching/model_context_pool.py
pvradar/sdk/caching/advisor/caching_advisor.py
pvradar/sdk/caching/advisor/remote_only_advisor.py
pvradar/sdk/caching/key_maker/caching_key_maker.py
pvradar/sdk/caching/key_maker/caching_key_maker_project.py
pvradar/sdk/caching/key_maker/caching_key_maker_pvradar_site.py
pvradar/sdk/caching/kv_storage/kv_storage_adaptor.py
pvradar/sdk/caching/kv_storage/kv_storage_binary_adaptor.py
pvradar/sdk/caching/kv_storage/kv_storage_file.py
pvradar/sdk/caching/kv_storage/kv_storage_lmdb.py
pvradar/sdk/caching/kv_storage/kv_storage_memory.py
pvradar/sdk/caching/kv_storage/kv_storage_with_expiration_adaptor.py
pvradar/sdk/client/__init__.py
pvradar/sdk/client/api_query.py
pvradar/sdk/client/client.py
pvradar/sdk/client/client_binder.py
pvradar/sdk/client/client_error_handling.py
pvradar/sdk/client/client_handler.py
pvradar/sdk/client/client_types.py
pvradar/sdk/client/client_utils.py
pvradar/sdk/client/pvradar_resources.py
pvradar/sdk/client/pvradar_site.py
pvradar/sdk/client/pvradar_validation.py
pvradar/sdk/client/sync_client.py
pvradar/sdk/client/dock/__init__.py
pvradar/sdk/client/dock/api_models.py
pvradar/sdk/client/dock/dock_client_utils.py
pvradar/sdk/client/dock/dock_sync_client.py
pvradar/sdk/client/engine/engine_types.py
pvradar/sdk/client/engine/engine_utils.py
pvradar/sdk/client/engine/step_table.py
pvradar/sdk/client/engine/step_table_types.py
pvradar/sdk/client/models/__init__.py
pvradar/sdk/client/models/aemet_grid_models.py
pvradar/sdk/client/models/era5_models.py
pvradar/sdk/client/models/ideam_models.py
pvradar/sdk/client/models/inmet_models.py
pvradar/sdk/client/models/merra2_models.py
pvradar/sdk/client/models/merra2_types.py
pvradar/sdk/client/models/noaa_models.py
pvradar_sdk-2.15.2.dist-info/LICENSE
pvradar_sdk-2.15.2.dist-info/METADATA
pvradar_sdk-2.15.2.dist-info/WHEEL
pvradar_sdk-2.15.2.dist-info/top_level.txt
pvradar_sdk-2.15.2.dist-info/RECORD
