Metadata-Version: 2.2
Name: pvradar-sdk
Version: 2.15.2
Summary: PVRADAR SDK
Author-email: Kostiantyn Pogorelov <kp@pvradar.com>
License: Copyright (c) 2025 PVRADAR Labs GmbH <info@pvradar.com> (https://pvradar.com)
Project-URL: homepage, https://pvradar.com
Classifier: Programming Language :: Python :: 3
Classifier: Operating System :: OS Independent
Requires-Python: <4.0,>=3.12
License-File: LICENSE
Requires-Dist: httpx>=0.27
Requires-Dist: pandas>=2.2.2
Requires-Dist: platformdirs>=4.2.1
Requires-Dist: pvlib>=0.11
Requires-Dist: pydantic>=2.8.2
Requires-Dist: scipy>=1.14.1
Requires-Dist: pint>=0.24
Requires-Dist: authlib>=1.3.2
Requires-Dist: nest-asyncio>=1.6.0
Requires-Dist: timezonefinder==6.5.8
Requires-Dist: orjson>=3.10.15
Requires-Dist: lmdb>=1.6.2
Requires-Dist: truststore>=0.10.0
Requires-Dist: geopy~=2.4.1
Requires-Dist: sympy~=1.14.0
Provides-Extra: dev
Requires-Dist: pytest==8.3.3; extra == "dev"
Requires-Dist: pyright==1.1.402; extra == "dev"
Requires-Dist: pandas-stubs==2.2.3.241126; extra == "dev"
Requires-Dist: ruff==0.9.3; extra == "dev"
Provides-Extra: plotly
Requires-Dist: plotly~=6.3.0; extra == "plotly"
Requires-Dist: nbformat>=4.2.0; extra == "plotly"
Provides-Extra: kaleido
Requires-Dist: plotly~=6.3.0; extra == "kaleido"
Requires-Dist: nbformat>=4.2.0; extra == "kaleido"
Requires-Dist: kaleido~=1.1.0; extra == "kaleido"
Provides-Extra: kgcpy
Requires-Dist: kgcpy~=1.1.8; extra == "kgcpy"
Provides-Extra: matplotlib
Requires-Dist: matplotlib~=3.10.0; extra == "matplotlib"
